{
  "name": "nullroute",
  "region": "nyc1",
  "services": [
    {
      "name": "api",
      "run_command": "pnpm start",
      "build_command": "pnpm install && pnpm build",
      "environment_slug": "node-js",
      "instance_count": 1,
      "instance_size_slug": "apps-s-1vcpu-0.5gb",
      "http_port": 8080,
      "github": {
        "repo": "AxsolTools/nullroute",
        "branch": "main",
        "deploy_on_push": true
      },
      "source_dir": "/",
      "routes": [
        {
          "path": "/"
        }
      ],
      "envs": [
        {
          "key": "NODE_ENV",
          "value": "production"
        },
        {
          "key": "CHANGENOW_API_KEY",
          "value": "8bce3912ce8d326dd7ec028a84e33c110767b44964e8cd78525dea6b406029d5",
          "scope": "RUN_TIME",
          "type": "SECRET"
        }
      ]
    }
  ]
}

